mykad_generator/__init__.py
mykad_generator/generator.py
mykad_generator-0.1.3.dist-info/METADATA
mykad_generator-0.1.3.dist-info/WHEEL
mykad_generator-0.1.3.dist-info/RECORD
