Metadata-Version: 2.3
Name: mykad-generator
Version: 0.1.3
Summary: Random Mykads for testing purposes. Returns list of mykad
Author: msaleel
Author-email: mohammed.saleel0099@gmail.com
Requires-Python: >=3.8
Classifier: Programming Language :: Python :: 3
Classifier: Programming Language :: Python :: 3.8
Classifier: Programming Language :: Python :: 3.9
Classifier: Programming Language :: Python :: 3.10
Classifier: Programming Language :: Python :: 3.11
Classifier: Programming Language :: Python :: 3.12
Classifier: Programming Language :: Python :: 3.13
